cog_sains_test_pack_utils/__init__.py
cog_sains_test_pack_utils/common_test_code.py
cogz_test_pack_utils-0.1.0.dist-info/METADATA
cogz_test_pack_utils-0.1.0.dist-info/WHEEL
cogz_test_pack_utils-0.1.0.dist-info/top_level.txt
cogz_test_pack_utils-0.1.0.dist-info/RECORD
