Metadata-Version: 2.1
Name: cogz-test-pack-utils
Version: 0.1.0
Summary: Shared Python Azure Utils Code for use in FunctionApps
